{
    "_links": {
        "self": {
            "href": "http:\/\/default\/taxonomy\/term\/3?_format=hal_json"
        },
        "type": {
            "href": "http:\/\/drupal.org\/rest\/type\/taxonomy_term\/sponsor_level"
        },
        "http:\/\/drupal.org\/rest\/relation\/taxonomy_term\/sponsor_level\/parent": [
            null
        ]
    },
    "tid": [
        {
            "value": 3
        }
    ],
    "uuid": [
        {
            "value": "72071ffd-c254-46f7-92cc-7b6a1d0cf1e0"
        }
    ],
    "langcode": [
        {
            "value": "en",
            "lang": "en"
        }
    ],
    "vid": [
        {
            "target_id": "sponsor_level"
        }
    ],
    "status": [
        {
            "value": true,
            "lang": "en"
        }
    ],
    "name": [
        {
            "value": "Supporting",
            "lang": "en"
        }
    ],
    "weight": [
        {
            "value": 2
        }
    ],
    "_embedded": {
        "http:\/\/drupal.org\/rest\/relation\/taxonomy_term\/sponsor_level\/parent": [
            null
        ]
    },
    "changed": [
        {
            "value": "2019-03-16T20:44:42+00:00",
            "lang": "en",
            "format": "Y-m-d\\TH:i:sP"
        }
    ],
    "default_langcode": [
        {
            "value": true,
            "lang": "en"
        }
    ],
    "metatag": [
        {
            "value": {
                "title": "Supporting | Bay Area Drupal Camp - 2019",
                "canonical_url": "http:\/\/default\/taxonomy\/term\/3"
            }
        }
    ]
}